tracserversideredirect/__init__.py
tracserversideredirect/plugin.py
TracServerSideRedirectPlugin-1.0.2.dist-info/COPYING
TracServerSideRedirectPlugin-1.0.2.dist-info/METADATA
TracServerSideRedirectPlugin-1.0.2.dist-info/WHEEL
TracServerSideRedirectPlugin-1.0.2.dist-info/dependency_links.txt
TracServerSideRedirectPlugin-1.0.2.dist-info/entry_points.txt
TracServerSideRedirectPlugin-1.0.2.dist-info/top_level.txt
TracServerSideRedirectPlugin-1.0.2.dist-info/RECORD
