Metadata-Version: 2.1
Name: TracServerSideRedirectPlugin
Version: 1.0.2
Summary: Server side redirect plugin for Trac.
Home-page: https://trac-hacks.org/wiki/ServerSideRedirectPlugin
Author: Martin Scharrer
Author-email: martin@scharrer-online.de
License: GPLv3 or 3-Clause BSD
Keywords: trac plugin server redirect
Platform: UNKNOWN
Classifier: Framework :: Trac
Requires-Dist: TracExtractUrl (>=0.5)
Requires-Dist: Trac
